<?xml version="1.0" encoding="utf-8"?><soap:Envelope xmlns:soap="http://schemas.xmlsoap.org/soap/envelope/" xmlns:xsi="http://www.w3.org/2001/XMLSchema-instance" xmlns:xsd="http://www.w3.org/2001/XMLSchema"><soap:Body><RequestTransactionResponse xmlns="http://www.fact.com.mx/schema/ws"><RequestTransactionResult><Request><Transaction>SYSTEM_REQUEST</Transaction><Requestor>8a454e3f-cea1-41d8-a13a-a748a4891bbe</Requestor><RequestorName /><RequestorActive>true</RequestorActive><Country>GT</Country><Entity>800000001026</Entity><User>8a454e3f-cea1-41d8-a13a-a748a4891bbe</User><UserName>TEST</UserName><Id>c5efd9fa-7401-4187-9fb9-09c932ed4445</Id><TimeStamp>2025-12-16T16:15:44.8541538-06:00</TimeStamp></Request><Response><Result>false</Result><TimeStamp>2025-12-16T16:15:45.0746593-06:00</TimeStamp><LastResult>XML_INVALID</LastResult><Code>997</Code><Description>Fallo la ejecucion del comando: [POST_DOCUMENT_SAT], TrCode: [997], description: [Element, dte:DatosEmision:  
Whitespace, : 
        Error en Validacion esquema: [El elemento 'DTE' en espacio de nombres 'http://www.sat.gob.gt/dte/fel/0.2.0' tiene un elemento secundario 'Complementos' en espacio de nombres 'http://www.sat.gob.gt/dte/fel/0.2.0' no válido. Lista esperada de elementos posibles: 'Certificacion' en espacio de nombres 'http://www.sat.gob.gt/dte/fel/0.2.0'.]]</Description><Hint>Error controlado</Hint><Data>Fallo la ejecucion del comando: [POST_DOCUMENT_SAT], TrCode: [997], description: [Element, dte:DatosEmision:  
Whitespace, : 
        Error en Validacion esquema: [El elemento 'DTE' en espacio de nombres 'http://www.sat.gob.gt/dte/fel/0.2.0' tiene un elemento secundario 'Complementos' en espacio de nombres 'http://www.sat.gob.gt/dte/fel/0.2.0' no válido. Lista esperada de elementos posibles: 'Certificacion' en espacio de nombres 'http://www.sat.gob.gt/dte/fel/0.2.0'.]]</Data></Response><ResponseData><ResponseData1 /><ResponseData2 /><ResponseData3 /></ResponseData></RequestTransactionResult></RequestTransactionResponse></soap:Body></soap:Envelope>